assistant_skills_lib/__init__.py
assistant_skills_lib/batch_processor.py
assistant_skills_lib/cache.py
assistant_skills_lib/config_manager.py
assistant_skills_lib/credential_manager.py
assistant_skills_lib/error_handler.py
assistant_skills_lib/formatters.py
assistant_skills_lib/project_detector.py
assistant_skills_lib/request_batcher.py
assistant_skills_lib/template_engine.py
assistant_skills_lib/validators.py
assistant_skills_lib/mock/__init__.py
assistant_skills_lib/mock/base.py
assistant_skills_lib-1.0.1.dist-info/METADATA
assistant_skills_lib-1.0.1.dist-info/WHEEL
assistant_skills_lib-1.0.1.dist-info/licenses/LICENSE
assistant_skills_lib-1.0.1.dist-info/RECORD
