Metadata-Version: 2.4
Name: assistant-skills-lib
Version: 1.0.1
Summary: Shared Python utilities for building Claude Code Assistant Skills plugins
Project-URL: Homepage, https://github.com/grandcamel/assistant-skills-lib
Project-URL: Repository, https://github.com/grandcamel/assistant-skills-lib
Project-URL: Issues, https://github.com/grandcamel/assistant-skills-lib/issues
Author: grandcamel
License-Expression: MIT
License-File: LICENSE
Keywords: assistant-skills,claude,claude-code,plugins,utilities
Classifier: Development Status :: 4 - Beta
Classifier: Intended Audience :: Developers
Classifier: License :: OSI Approved :: MIT License
Classifier: Operating System :: OS Independent
Classifier: Programming Language :: Python :: 3
Classifier: Programming Language :: Python :: 3.9
Classifier: Programming Language :: Python :: 3.10
Classifier: Programming Language :: Python :: 3.11
Classifier: Programming Language :: Python :: 3.12
Classifier: Topic :: Software Development :: Libraries :: Python Modules
Requires-Python: >=3.9
Requires-Dist: requests>=2.28.0
Requires-Dist: tabulate>=0.9.0
Provides-Extra: all
Requires-Dist: mypy>=1.0.0; extra == 'all'
Requires-Dist: pytest-cov>=4.0.0; extra == 'all'
Requires-Dist: pytest>=7.0.0; extra == 'all'
Requires-Dist: ruff>=0.1.0; extra == 'all'
Provides-Extra: dev
Requires-Dist: mypy>=1.0.0; extra == 'dev'
Requires-Dist: pytest-cov>=4.0.0; extra == 'dev'
Requires-Dist: pytest>=7.0.0; extra == 'dev'
Requires-Dist: ruff>=0.1.0; extra == 'dev'
Provides-Extra: http
